{"rooms": {"CJ6YB": {"id": "CJ6YB", "name": "Tech Quiz1", "topic": "Computer Science", "max_players": 5, "questions": [{"id": "1", "text": "What is the capital of computer science?", "options": ["Python", "C++", "Algorithm", "Turing"], "correct_answer": "Turing"}, {"id": "2", "text": "Which programming language is used for building Android apps?", "options": ["Java", "Python", "C#", "Ruby"], "correct_answer": "Java"}, {"id": "3", "text": "What does HTML stand for?", "options": ["Hypertext Markup Language", "Hyper Tool Markup Language", "Home Tool Markup Language", "Hyperlinks and Text Markup Language"], "correct_answer": "Hypertext Markup Language"}, {"id": "4", "text": "Which data structure uses First In First Out (FIFO) approach?", "options": ["Stack", "Queue", "Tree", "Linked List"], "correct_answer": "Queue"}, {"id": "5", "text": "What does CPU stand for?", "options": ["Central Processing Unit", "Computer Processing Unit", "Central Program Unit", "Computer Peripheral Unit"], "correct_answer": "Central Processing Unit"}], "players": ["Admin-CJ6", "Player1"], "admin_id": "cdeb35f8-dccf-46c8-83b9-69e52534e8c8", "current_question": 0, "scores": {"Admin-CJ6": 0, "Player1": 0}, "started": true, "created_at": 1745514070.901222, "answered_correctly": {"Admin-CJ6": [], "Player1": []}}, "S7XEN": {"id": "S7XEN", "name": "Tech Quiz1.0", "topic": "Computer Science", "max_players": 5, "questions": [{"id": "06cca298-68c0-404e-aab9-8d6a36c94397", "text": "Question 1 about Computer Science?", "options": ["Option A", "Option B", "Option C", "Option D"], "correct_answer": "Option A"}, {"id": "774290ea-3e5a-447d-9ceb-1951106c3ddc", "text": "Question 2 about Computer Science?", "options": ["Option A", "Option B", "Option C", "Option D"], "correct_answer": "Option B"}], "players": ["Admin-S7X"], "admin_id": "6a88a8bd-73cd-402b-9fca-617318e8ad15", "current_question": 0, "scores": {"Admin-S7X": 0}, "started": true, "created_at": 1745514257.4926076, "answered_correctly": {"Admin-S7X": []}}, "JL4G2": {"id": "JL4G2", "name": "Shreekant", "topic": "Computer Science 10 questions", "max_players": 5, "questions": [{"id": "b3490229-cff8-433c-a2ab-a0b997ad55c3", "text": "Question 1 about Computer Science 10 questions?", "options": ["Option A", "Option B", "Option C", "Option D"], "correct_answer": "Option A"}, {"id": "88dd97c6-e072-46ba-b596-7da4d875c145", "text": "Question 2 about Computer Science 10 questions?", "options": ["Option A", "Option B", "Option C", "Option D"], "correct_answer": "Option B"}], "players": ["Admin-JL4", "Player1"], "admin_id": "34f3ffc5-407c-40a3-b7a6-062b807054a5", "current_question": 0, "scores": {"Admin-JL4": 1, "Player1": 1}, "started": true, "created_at": 1745514643.640198, "answered_correctly": {"Admin-JL4": ["b3490229-cff8-433c-a2ab-a0b997ad55c3"], "Player1": ["b3490229-cff8-433c-a2ab-a0b997ad55c3"]}}, "MRCEF": {"id": "MRCEF", "name": "Shreekant 1", "topic": "Computer Science 10 questions", "max_players": 5, "questions": [{"id": "1", "text": "What is the process of converting a high-level programming language code into machine code called?", "options": ["Compilation", "Execution", "Debugging", "Interpretation"], "correct_answer": "Compilation"}, {"id": "2", "text": "Which data structure uses Last In First Out (LIFO) principle?", "options": ["Queue", "Hash Table", "Stack", "Linked List"], "correct_answer": "Stack"}, {"id": "3", "text": "What does CPU stand for?", "options": ["Central Processing Unit", "Computer Processing Unit", "Control Processing Unit", "Compact Processing Unit"], "correct_answer": "Central Processing Unit"}, {"id": "4", "text": "Which sorting algorithm has the best worst-case time complexity?", "options": ["Bubble Sort", "Insertion Sort", "Merge Sort", "Selection Sort"], "correct_answer": "Merge Sort"}, {"id": "5", "text": "In object-oriented programming, what is the concept of creating new classes by extending existing classes known as?", "options": ["Inheritance", "Polymorphism", "Encapsulation", "Abstraction"], "correct_answer": "Inheritance"}], "players": ["Admin-MRC", "Tanmay", "Parmeshwar"], "admin_id": "3f141307-8ecc-4371-b782-aa03ad1155b6", "current_question": 0, "scores": {"Admin-MRC": 0, "Tanmay": 0, "Parmeshwar": 1}, "started": true, "created_at": 1745516380.564482, "answered_correctly": {"Admin-MRC": [], "Tanmay": [], "Parmeshwar": ["1"]}}, "TTDU3": {"id": "TTDU3", "name": "Shreekant 1.1", "topic": "Computer Science 10 questions", "max_players": 5, "questions": [{"id": "1", "text": "Which event is associated with the hashtag #ElonMusk?", "options": ["Coachella2025", "Elon Musk", "PahalgamTerroristAttack", "ENHYPEN"], "correct_answer": "Elon Musk"}, {"id": "2", "text": "What is the theme of the hashtag #AprilFoolsDay?", "options": ["Perfect10LinersFinalEP", "April Fools' Day", "Encella", "NintendoSwitch2"], "correct_answer": "April Fools' Day"}, {"id": "3", "text": "Which hashtag is related to a music festival?", "options": ["JENCHELLA", "SongkranCTWxFB", "Earthquake", "Riyadh"], "correct_answer": "JENCHELLA"}, {"id": "4", "text": "What is the trending topic related to a new product launch?", "options": ["Goodbadugly", "Riyadh", "NintendoSwitch2", "Enhypen"], "correct_answer": "NintendoSwitch2"}, {"id": "5", "text": "Which hashtag is associated with a cultural event or festival?", "options": ["PahalgamTerroristAttack", "ENHYPEN", "Lisachella", "4\u0e1b\u0e48\u0e32\u0e0a\u0e49\u0e32\u0e41\u0e15\u0e01"], "correct_answer": "Lisachella"}], "players": ["Admin-TTD", "Parmeshwar"], "admin_id": "67b8879c-b6c9-4bc8-bda6-502f9c8620db", "current_question": 0, "scores": {"Admin-TTD": 0, "Parmeshwar": 0}, "started": false, "created_at": 1745520168.2752302, "answered_correctly": {"Admin-TTD": [], "Parmeshwar": []}}, "GUN6W": {"id": "GUN6W", "name": "Shreekant 1.2.1", "topic": "Computer Science 10 questions", "max_players": 5, "questions": [{"id": "9eca2e6f-009c-4edd-89c6-7b6877ff749f", "text": "Which of these hashtags related to Computer Science 10 questions trended the longest in India this week?", "options": ["#Computer Science 10 questionsFest", "#Computer Science 10 questionsControversy", "#Computer Science 10 questionsMemes", "#Computer Science 10 questionsNews"], "correct_answer": "#Computer Science 10 questionsMemes", "difficulty": "medium", "category": "current events"}, {"id": "3cee7bc6-38cc-4538-9e31-106cd4856965", "text": "Which platform recently introduced a feature similar to Twitter's retweet?", "options": ["LinkedIn", "TikTok", "Pinterest", "WhatsApp"], "correct_answer": "LinkedIn", "difficulty": "hard", "category": "internet culture"}], "players": ["Admin-GUN"], "admin_id": "c6343f3a-df58-412b-b608-b28aa4764cf6", "current_question": 0, "scores": {"Admin-GUN": 0}, "started": false, "created_at": 1745528622.257644, "answered_correctly": {"Admin-GUN": []}}, "N9QY4": {"id": "N9QY4", "name": "Shreekant 1.2.1.2", "topic": "Computer Science 10 questions", "max_players": 5, "questions": [{"id": "25e1cdc2-1cc0-44b1-9dde-7ac36b067f5f", "text": "Which of these hashtags related to Computer Science 10 questions trended the longest in India this week?", "options": ["#Computer Science 10 questionsFest", "#Computer Science 10 questionsControversy", "#Computer Science 10 questionsMemes", "#Computer Science 10 questionsNews"], "correct_answer": "#Computer Science 10 questionsMemes", "difficulty": "medium", "category": "current events"}, {"id": "3941e310-4dc2-4e2f-9c6c-f28580c768c3", "text": "Which platform recently introduced a feature similar to Twitter's retweet?", "options": ["LinkedIn", "TikTok", "Pinterest", "WhatsApp"], "correct_answer": "LinkedIn", "difficulty": "hard", "category": "internet culture"}], "players": ["Admin-N9Q", "Tanmay"], "admin_id": "cff8951d-5674-49e3-b52e-55bc2e8d5b4a", "current_question": 0, "scores": {"Admin-N9Q": 0, "Tanmay": 0}, "started": false, "created_at": 1745528645.5506916, "answered_correctly": {"Admin-N9Q": [], "Tanmay": []}}, "WDZ77": {"id": "WDZ77", "name": "Shreekant 1.2.1.2.8", "topic": "StockMarket", "max_players": 5, "questions": [{"id": "0f4e1afc-4590-40a9-b6b5-4d0660519dad", "text": "Question 1 about StockMarket?", "options": ["Option A", "Option B", "Option C", "Option D"], "correct_answer": "Option A"}, {"id": "ae5b57af-c647-4f85-a6f2-91ad07efa756", "text": "Question 2 about StockMarket?", "options": ["Option A", "Option B", "Option C", "Option D"], "correct_answer": "Option B"}], "players": ["Admin-WDZ", "Tanmay"], "admin_id": "edec8190-e567-48f0-b2cb-fdd1871ecf64", "current_question": 0, "scores": {"Admin-WDZ": 0, "Tanmay": 0}, "started": false, "created_at": 1745528777.4388192, "answered_correctly": {"Admin-WDZ": [], "Tanmay": []}}, "QQPUC": {"id": "QQPUC", "name": "Shreekant 1.2.1.2.8.2", "topic": "StockMarket", "max_players": 5, "questions": [{"id": "2e684d31-120a-47d4-8dfe-b60399f08ee3", "text": "Which of these hashtags related to StockMarket trended the longest in India this week?", "options": ["#StockMarketFest", "#StockMarketControversy", "#StockMarketMemes", "#StockMarketNews"], "correct_answer": "#StockMarketMemes", "difficulty": "medium", "category": "current events"}, {"id": "d95fddb2-5fe7-42b0-9fd7-989aca8fdae5", "text": "Which platform recently introduced a feature similar to Twitter's retweet?", "options": ["LinkedIn", "TikTok", "Pinterest", "WhatsApp"], "correct_answer": "LinkedIn", "difficulty": "hard", "category": "internet culture"}], "players": ["Admin-QQP", "Tanmay"], "admin_id": "8ef904f2-1fe0-4da8-9665-100e890f4619", "current_question": 0, "scores": {"Admin-QQP": 0, "Tanmay": 0}, "started": false, "created_at": 1745528929.2742028, "answered_correctly": {"Admin-QQP": [], "Tanmay": []}}, "2PYNM": {"id": "2PYNM", "name": "Shreekant 1.2.1.2.8.2.0", "topic": "StockMarket", "max_players": 5, "questions": [{"id": "cdc684d4-91f8-4e1d-af5c-45bff7e2c825", "text": "Which of these hashtags related to StockMarket trended the longest in India this week?", "options": ["#StockMarketFest", "#StockMarketControversy", "#StockMarketMemes", "#StockMarketNews"], "correct_answer": "#StockMarketMemes", "difficulty": "medium", "category": "current events"}, {"id": "554789f4-9df1-4a34-9c50-95f07aaa4857", "text": "Which platform recently introduced a feature similar to Twitter's retweet?", "options": ["LinkedIn", "TikTok", "Pinterest", "WhatsApp"], "correct_answer": "LinkedIn", "difficulty": "hard", "category": "internet culture"}], "players": ["Admin-2PY", "Tanmay"], "admin_id": "e8384701-12eb-4e80-af0b-1d72831ae6c4", "current_question": 0, "scores": {"Admin-2PY": 0, "Tanmay": 0}, "started": false, "created_at": 1745528958.7987883, "answered_correctly": {"Admin-2PY": [], "Tanmay": []}}, "NRBK7": {"id": "NRBK7", "name": "Shreekant 1.2.1.2.8.2.0.2", "topic": "Sports", "max_players": 5, "questions": [{"id": "23b93422-a976-4d29-b84c-486262ea3a2a", "text": "Which of these hashtags related to Sports trended the longest in India this week?", "options": ["#SportsFest", "#SportsControversy", "#SportsMemes", "#SportsNews"], "correct_answer": "#SportsMemes", "difficulty": "medium", "category": "current events"}, {"id": "0667bb63-0f11-4e39-9fc7-4d9cd89e1dd4", "text": "Which platform recently introduced a feature similar to Twitter's retweet?", "options": ["LinkedIn", "TikTok", "Pinterest", "WhatsApp"], "correct_answer": "LinkedIn", "difficulty": "hard", "category": "internet culture"}], "players": ["Admin-NRB", "Tanmay"], "admin_id": "af89e852-83c1-4f24-bc9b-1c665fce9abb", "current_question": 0, "scores": {"Admin-NRB": 0, "Tanmay": 0}, "started": false, "created_at": 1745529000.4341373, "answered_correctly": {"Admin-NRB": [], "Tanmay": []}}, "CMPNK": {"id": "CMPNK", "name": "Shreekant 1.2.1.2.8.2.0.2.3", "topic": "Sports", "max_players": 5, "questions": [{"id": "844393fc-403a-4b46-81e8-df46f5d3478a", "text": "Which company's stock had the biggest pre-market move this morning?", "options": ["Tesla (TSLA)", "NVIDIA (NVDA)", "Reliance Industries (RELIANCE.NS)", "BYD (BYDDF)"], "correct_answer": "NVIDIA (NVDA)", "difficulty": "hard", "category": "stocks", "timestamp": 1745529122.2832034}, {"id": "bd5d25ef-6e21-4196-b4b8-7da1d1eb68a8", "text": "Which cryptocurrency just announced a major protocol upgrade this week?", "options": ["Bitcoin (Layer 2 solution)", "Ethereum (Dencun upgrade)", "Solana (Firedancer)", "Cardano (Hydra)"], "correct_answer": "Ethereum (Dencun upgrade)", "difficulty": "medium", "category": "crypto", "timestamp": 1745529122.2832034}], "players": ["Admin-CMP", "Tanmay"], "admin_id": "ddcf66f8-5ea5-42ee-9830-39b43ee89b0d", "current_question": 0, "scores": {"Admin-CMP": 0, "Tanmay": 0}, "started": false, "created_at": 1745529122.2832034, "answered_correctly": {"Admin-CMP": [], "Tanmay": []}}, "3UM29": {"id": "3UM29", "name": "Shreekant 1.2.1.2.8.2.0.2.3.2", "topic": "Sports", "max_players": 5, "questions": [{"id": "c221ae5a-604a-4763-89de-50d3fd8bfafa", "text": "Which company's stock had the biggest pre-market move this morning?", "options": ["Tesla (TSLA)", "NVIDIA (NVDA)", "Reliance Industries (RELIANCE.NS)", "BYD (BYDDF)"], "correct_answer": "NVIDIA (NVDA)", "difficulty": "hard", "category": "stocks", "timestamp": 1745529538.425564}, {"id": "bef8b08b-499e-40c7-b229-7ba6903eb7ca", "text": "Which cryptocurrency just announced a major protocol upgrade this week?", "options": ["Bitcoin (Layer 2 solution)", "Ethereum (Dencun upgrade)", "Solana (Firedancer)", "Cardano (Hydra)"], "correct_answer": "Ethereum (Dencun upgrade)", "difficulty": "medium", "category": "crypto", "timestamp": 1745529538.425564}], "players": ["Admin-3UM", "Tanmay"], "admin_id": "ecb469c2-cfba-4714-9be0-ca81a37e6dc2", "current_question": 0, "scores": {"Admin-3UM": 0, "Tanmay": 0}, "started": false, "created_at": 1745529538.426692, "answered_correctly": {"Admin-3UM": [], "Tanmay": []}}, "82X3G": {"id": "82X3G", "name": "Shreekant 1.2.1.2.8.2.0.2.3.2.3", "topic": "Sports", "max_players": 5, "questions": [{"id": "aa6b42d1-c45d-4509-8653-64583e71476b", "text": "Which company's stock surged after a major product announcement?", "options": ["Apple (AAPL)", "Microsoft (MSFT)", "Tesla (TSLA)", "Amazon (AMZN)"], "correct_answer": "Apple (AAPL)", "difficulty": "medium", "category": "stock market", "explanation": "Apple announced a new product line, boosting its stock.", "timestamp": 1745530156.7266526}, {"id": "234dcab3-f43f-49bc-b953-c27b66755ad6", "text": "Which stock fell due to a recent earnings miss?", "options": ["Google (GOOGL)", "Facebook (META)", "Netflix (NFLX)", "Intel (INTC)"], "correct_answer": "Netflix (NFLX)", "difficulty": "medium", "category": "stock market", "explanation": "Netflix reported lower-than-expected subscriber growth.", "timestamp": 1745530156.7266526}], "players": ["Admin-82X", "Tanmay"], "admin_id": "910a0741-a6a8-4eff-87ef-d31153b4596d", "current_question": 0, "scores": {"Admin-82X": 0, "Tanmay": 0}, "started": false, "created_at": 1745530156.7266526, "answered_correctly": {"Admin-82X": [], "Tanmay": []}}, "6SPG4": {"id": "6SPG4", "name": "Shreekant 1.2.1.2.8.2.0.2.3.22..3", "topic": "Sports", "max_players": 5, "questions": [{"id": "7142e254-782c-4490-b1cb-c8d3d8cea9b2", "text": "Which company's stock had the biggest pre-market move this morning?", "options": ["Tesla (TSLA)", "NVIDIA (NVDA)", "Reliance Industries (RELIANCE.NS)", "BYD (BYDDF)"], "correct_answer": "NVIDIA (NVDA)", "difficulty": "hard", "category": "stocks", "timestamp": 1745530228.5777044}, {"id": "0262ed26-44b5-4ba1-8034-5822dfd7cade", "text": "Which cryptocurrency just announced a major protocol upgrade this week?", "options": ["Bitcoin (Layer 2 solution)", "Ethereum (Dencun upgrade)", "Solana (Firedancer)", "Cardano (Hydra)"], "correct_answer": "Ethereum (Dencun upgrade)", "difficulty": "medium", "category": "crypto", "timestamp": 1745530228.5777044}], "players": ["Admin-6SP", "Tanmay"], "admin_id": "ef88fa7d-7c09-40dc-8b4e-454cb284bf57", "current_question": 0, "scores": {"Admin-6SP": 0, "Tanmay": 0}, "started": false, "created_at": 1745530228.5777044, "answered_correctly": {"Admin-6SP": [], "Tanmay": []}}, "KDEAM": {"id": "KDEAM", "name": "Shreekant 1.2.1.2.8.2.0.2.3.s22..3", "topic": "Sports", "max_players": 5, "questions": [{"id": "63f91b33-182d-425b-9497-ed550f12cc2a", "text": "Which company's stock surged after a major product announcement?", "options": ["Apple (AAPL)", "Microsoft (MSFT)", "Tesla (TSLA)", "Amazon (AMZN)"], "correct_answer": "Apple (AAPL)", "difficulty": "medium", "category": "stock market", "explanation": "Apple announced a new product line, boosting its stock.", "timestamp": 1745530480.4705653}, {"id": "9e711e06-ab63-4e39-8e03-f7a7f991ccc2", "text": "Which stock fell due to a recent earnings miss?", "options": ["Google (GOOGL)", "Facebook (META)", "Netflix (NFLX)", "Intel (INTC)"], "correct_answer": "Netflix (NFLX)", "difficulty": "medium", "category": "stock market", "explanation": "Netflix reported lower-than-expected subscriber growth.", "timestamp": 1745530480.4705653}], "players": ["Admin-KDE"], "admin_id": "da51197a-43a8-4cd3-bc2e-b5e78662e962", "current_question": 0, "scores": {"Admin-KDE": 0}, "started": false, "created_at": 1745530480.4714289, "answered_correctly": {"Admin-KDE": []}}, "PXDSF": {"id": "PXDSF", "name": "Shreekant 1.2.1.2.8.2.0.2.3.xs22..3", "topic": "Sports", "max_players": 5, "questions": [{"id": "e2505f3a-0f87-4de3-94e3-3634656d02a1", "text": "Which company's stock surged after a major product announcement?", "options": ["Apple (AAPL)", "Microsoft (MSFT)", "Tesla (TSLA)", "Amazon (AMZN)"], "correct_answer": "Apple (AAPL)", "difficulty": "medium", "category": "stock market", "explanation": "Apple announced a new product line, boosting its stock.", "timestamp": 1745530687.176978}, {"id": "75190500-b68f-4347-a1e7-90c3a86f3869", "text": "Which stock fell due to a recent earnings miss?", "options": ["Google (GOOGL)", "Facebook (META)", "Netflix (NFLX)", "Intel (INTC)"], "correct_answer": "Netflix (NFLX)", "difficulty": "medium", "category": "stock market", "explanation": "Netflix reported lower-than-expected subscriber growth.", "timestamp": 1745530687.176978}], "players": ["Admin-PXD"], "admin_id": "2882656b-7f4c-4991-a2ca-8f50b251c69a", "current_question": 0, "scores": {"Admin-PXD": 0}, "started": false, "created_at": 1745530687.1789806, "answered_correctly": {"Admin-PXD": []}}, "3EHYK": {"id": "3EHYK", "name": "Shreekant 1.2.1.2.8.2s.0.2.3.xs22..3", "topic": "Sports", "max_players": 5, "questions": [{"id": "382aaaf9-8ac0-4f5a-83f6-b36b614edc0c", "text": "What percentage did Apple Inc. (AAPL) stock increase by in the last 24 hours?", "options": ["5%", "2%", "10%", "3%"], "correct_answer": "3%", "difficulty": "medium", "category": "stock market", "explanation": "Apple stock increased by 3% due to positive earnings reports.", "timestamp": 1745530773.2825625}, {"id": "6e3ff4f0-92b7-4ac0-a329-6b40cbfe5b7b", "text": "By how much did Tesla Inc. (TSLA) stock decrease in the last 24 hours?", "options": ["2%", "5%", "1%", "3%"], "correct_answer": "1%", "difficulty": "medium", "category": "stock market", "explanation": "Tesla stock decreased by 1% amidst concerns about production delays.", "timestamp": 1745530773.2825625}, {"id": "4f169f21-7073-4bb1-acd6-e4558af56435", "text": "What was the percentage change in Amazon.com Inc. (AMZN) stock in the last 24 hours?", "options": ["4%", "1%", "6%", "2%"], "correct_answer": "4%", "difficulty": "medium", "category": "stock market", "explanation": "Amazon stock increased by 4% following a strong earnings report.", "timestamp": 1745530773.2825625}, {"id": "f434384f-92d3-402d-ac64-07e6d50200e5", "text": "How much did Microsoft Corporation (MSFT) stock increase by in the last 24 hours?", "options": ["3%", "1%", "5%", "2%"], "correct_answer": "2%", "difficulty": "medium", "category": "stock market", "explanation": "Microsoft stock saw a 2% increase after announcing a new partnership.", "timestamp": 1745530773.2825625}, {"id": "db951cd3-a2fb-4a5c-bf60-9f57a5dc5266", "text": "What was the percentage change in Facebook Inc. (FB) stock in the last 24 hours?", "options": ["2%", "4%", "1%", "3%"], "correct_answer": "1%", "difficulty": "medium", "category": "stock market", "explanation": "Facebook stock decreased by 1% due to privacy concerns.", "timestamp": 1745530773.2825625}], "players": ["Admin-3EH", "Tanmay"], "admin_id": "5938291e-b307-45bf-a204-f1e08f75b9d8", "current_question": 0, "scores": {"Admin-3EH": 0, "Tanmay": 0}, "started": false, "created_at": 1745530773.2835586, "answered_correctly": {"Admin-3EH": [], "Tanmay": []}}, "NMJJU": {"id": "NMJJU", "name": "Shreekant 1.2.1hjhj.2.8.2ssd.0sd2.3.xs22..3", "topic": "Sports", "max_players": 5, "questions": [{"id": "c9764b1a-1ffd-446c-a9ff-99d0e46a525f", "text": "Which company's stock surged after a major product announcement?", "options": ["Apple (AAPL)", "Microsoft (MSFT)", "Tesla (TSLA)", "Amazon (AMZN)"], "correct_answer": "Apple (AAPL)", "difficulty": "medium", "category": "stock market", "explanation": "Apple announced a new product line, boosting its stock.", "timestamp": 1745531672.6848013}, {"id": "8b88c7b0-0f73-4c6a-a6d3-58abb1d3a53c", "text": "Which stock fell due to a recent earnings miss?", "options": ["Google (GOOGL)", "Facebook (META)", "Netflix (NFLX)", "Intel (INTC)"], "correct_answer": "Netflix (NFLX)", "difficulty": "medium", "category": "stock market", "explanation": "Netflix reported lower-than-expected subscriber growth.", "timestamp": 1745531672.6848013}], "players": ["Admin-NMJ"], "admin_id": "159cb1fa-2521-4363-b67c-d94ebca57859", "current_question": 0, "scores": {"Admin-NMJ": 0}, "started": false, "created_at": 1745531672.6848013, "answered_correctly": {"Admin-NMJ": []}}, "7N6DC": {"id": "7N6DC", "name": "Shreekant 1.2.1hjhj.2.8.2ssd.0sd2.xz3.xs22..3", "topic": "Sports", "max_players": 5, "questions": [{"id": "c8a05bdf-07c8-4874-807d-eb57011742c2", "text": "Which company's stock surged after a major product announcement?", "options": ["Apple (AAPL)", "Microsoft (MSFT)", "Tesla (TSLA)", "Amazon (AMZN)"], "correct_answer": "Apple (AAPL)", "difficulty": "medium", "category": "stock market", "explanation": "Apple announced a new product line, boosting its stock.", "timestamp": 1745531748.3711407}, {"id": "8248a4c2-4a80-453f-8318-40ed1c7aaa3c", "text": "Which stock fell due to a recent earnings miss?", "options": ["Google (GOOGL)", "Facebook (META)", "Netflix (NFLX)", "Intel (INTC)"], "correct_answer": "Netflix (NFLX)", "difficulty": "medium", "category": "stock market", "explanation": "Netflix reported lower-than-expected subscriber growth.", "timestamp": 1745531748.3711407}], "players": ["Admin-7N6"], "admin_id": "06cf0080-946e-4fa8-8c84-021cb5d8aa58", "current_question": 0, "scores": {"Admin-7N6": 0}, "started": false, "created_at": 1745531748.3711407, "answered_correctly": {"Admin-7N6": []}}, "FB72W": {"id": "FB72W", "name": "Shreekant 1.2.1hjhj.2.8.2ssd.0sdvbvb2.xz3.xs22..3", "topic": "Sports", "max_players": 5, "questions": [{"id": "81bbb597-f3d7-4a75-980c-e9299f8cf31a", "text": "Which company's stock surged after a major product announcement?", "options": ["Apple (AAPL)", "Microsoft (MSFT)", "Tesla (TSLA)", "Amazon (AMZN)"], "correct_answer": "Apple (AAPL)", "difficulty": "medium", "category": "stock market", "explanation": "Apple announced a new product line, boosting its stock.", "timestamp": 1745532348.3142745}, {"id": "f5535623-39ac-40e2-b875-7d6b14e736bd", "text": "Which stock fell due to a recent earnings miss?", "options": ["Google (GOOGL)", "Facebook (META)", "Netflix (NFLX)", "Intel (INTC)"], "correct_answer": "Netflix (NFLX)", "difficulty": "medium", "category": "stock market", "explanation": "Netflix reported lower-than-expected subscriber growth.", "timestamp": 1745532348.3142745}], "players": ["Admin-FB7"], "admin_id": "de7e57fa-0972-40f2-aec3-304cfab4673d", "current_question": 0, "scores": {"Admin-FB7": 0}, "started": false, "created_at": 1745532348.3142745, "answered_correctly": {"Admin-FB7": []}}}, "users": {"cdeb35f8-dccf-46c8-83b9-69e52534e8c8": {"id": "cdeb35f8-dccf-46c8-83b9-69e52534e8c8", "username": "Admin-CJ6", "current_room": "CJ6YB", "score": 0, "is_admin": true, "joined_at": 1745514070.901222}, "44a6bc9b-932d-4adf-856f-de2561d755db": {"id": "44a6bc9b-932d-4adf-856f-de2561d755db", "username": "Player1", "current_room": "CJ6YB", "score": 0, "is_admin": false, "joined_at": 1745514124.6900604}, "6a88a8bd-73cd-402b-9fca-617318e8ad15": {"id": "6a88a8bd-73cd-402b-9fca-617318e8ad15", "username": "Admin-S7X", "current_room": "S7XEN", "score": 0, "is_admin": true, "joined_at": 1745514257.4926076}, "34f3ffc5-407c-40a3-b7a6-062b807054a5": {"id": "34f3ffc5-407c-40a3-b7a6-062b807054a5", "username": "Admin-JL4", "current_room": "JL4G2", "score": 1, "is_admin": true, "joined_at": 1745514643.640198}, "579cf237-aa47-4242-93a8-c65280c39413": {"id": "579cf237-aa47-4242-93a8-c65280c39413", "username": "Player1", "current_room": "JL4G2", "score": 1, "is_admin": false, "joined_at": 1745514659.9112115}, "3f141307-8ecc-4371-b782-aa03ad1155b6": {"id": "3f141307-8ecc-4371-b782-aa03ad1155b6", "username": "Admin-MRC", "current_room": "MRCEF", "score": 0, "is_admin": true, "joined_at": 1745516380.564482}, "2fbd5623-8f89-4a2b-9c0f-529ce5a038fe": {"id": "2fbd5623-8f89-4a2b-9c0f-529ce5a038fe", "username": "Tanmay", "current_room": "MRCEF", "score": 0, "is_admin": false, "joined_at": 1745516400.7897289}, "2bb4196d-a21b-4519-afc6-caa1ec5a4dbf": {"id": "2bb4196d-a21b-4519-afc6-caa1ec5a4dbf", "username": "Parmeshwar", "current_room": "MRCEF", "score": 1, "is_admin": false, "joined_at": 1745516411.5245485}, "67b8879c-b6c9-4bc8-bda6-502f9c8620db": {"id": "67b8879c-b6c9-4bc8-bda6-502f9c8620db", "username": "Admin-TTD", "current_room": "TTDU3", "score": 0, "is_admin": true, "joined_at": 1745520168.2752302}, "aea72923-a9e4-458e-bd0f-1151d79724ba": {"id": "aea72923-a9e4-458e-bd0f-1151d79724ba", "username": "Parmeshwar", "current_room": "TTDU3", "score": 0, "is_admin": false, "joined_at": 1745520178.3866289}, "c6343f3a-df58-412b-b608-b28aa4764cf6": {"id": "c6343f3a-df58-412b-b608-b28aa4764cf6", "username": "Admin-GUN", "current_room": "GUN6W", "score": 0, "is_admin": true, "joined_at": 1745528622.257644}, "cff8951d-5674-49e3-b52e-55bc2e8d5b4a": {"id": "cff8951d-5674-49e3-b52e-55bc2e8d5b4a", "username": "Admin-N9Q", "current_room": "N9QY4", "score": 0, "is_admin": true, "joined_at": 1745528645.5506916}, "8131606a-4e48-473f-8461-e90cafde9706": {"id": "8131606a-4e48-473f-8461-e90cafde9706", "username": "Tanmay", "current_room": "N9QY4", "score": 0, "is_admin": false, "joined_at": 1745528744.1952698}, "edec8190-e567-48f0-b2cb-fdd1871ecf64": {"id": "edec8190-e567-48f0-b2cb-fdd1871ecf64", "username": "Admin-WDZ", "current_room": "WDZ77", "score": 0, "is_admin": true, "joined_at": 1745528777.4388192}, "fcac28db-77fb-41a8-9e82-f7c5b40ccf5e": {"id": "fcac28db-77fb-41a8-9e82-f7c5b40ccf5e", "username": "Tanmay", "current_room": "WDZ77", "score": 0, "is_admin": false, "joined_at": 1745528784.4873748}, "8ef904f2-1fe0-4da8-9665-100e890f4619": {"id": "8ef904f2-1fe0-4da8-9665-100e890f4619", "username": "Admin-QQP", "current_room": "QQPUC", "score": 0, "is_admin": true, "joined_at": 1745528929.2742028}, "45afd0a7-efd8-464e-8ed9-d29bc8f0a273": {"id": "45afd0a7-efd8-464e-8ed9-d29bc8f0a273", "username": "Tanmay", "current_room": "QQPUC", "score": 0, "is_admin": false, "joined_at": 1745528936.2328112}, "e8384701-12eb-4e80-af0b-1d72831ae6c4": {"id": "e8384701-12eb-4e80-af0b-1d72831ae6c4", "username": "Admin-2PY", "current_room": "2PYNM", "score": 0, "is_admin": true, "joined_at": 1745528958.7987883}, "514073cb-0c2c-4c63-be77-826f075fe91a": {"id": "514073cb-0c2c-4c63-be77-826f075fe91a", "username": "Tanmay", "current_room": "2PYNM", "score": 0, "is_admin": false, "joined_at": 1745528966.7739894}, "af89e852-83c1-4f24-bc9b-1c665fce9abb": {"id": "af89e852-83c1-4f24-bc9b-1c665fce9abb", "username": "Admin-NRB", "current_room": "NRBK7", "score": 0, "is_admin": true, "joined_at": 1745529000.4341373}, "d24d99f7-a741-448d-950e-7e38164767ad": {"id": "d24d99f7-a741-448d-950e-7e38164767ad", "username": "Tanmay", "current_room": "NRBK7", "score": 0, "is_admin": false, "joined_at": 1745529007.1386905}, "ddcf66f8-5ea5-42ee-9830-39b43ee89b0d": {"id": "ddcf66f8-5ea5-42ee-9830-39b43ee89b0d", "username": "Admin-CMP", "current_room": "CMPNK", "score": 0, "is_admin": true, "joined_at": 1745529122.2832034}, "f6216411-aa79-4c87-8a4d-081477ddfc6d": {"id": "f6216411-aa79-4c87-8a4d-081477ddfc6d", "username": "Tanmay", "current_room": "CMPNK", "score": 0, "is_admin": false, "joined_at": 1745529130.2629702}, "ecb469c2-cfba-4714-9be0-ca81a37e6dc2": {"id": "ecb469c2-cfba-4714-9be0-ca81a37e6dc2", "username": "Admin-3UM", "current_room": "3UM29", "score": 0, "is_admin": true, "joined_at": 1745529538.426692}, "d399fe5f-4fc8-4420-afc7-735f155b5a8e": {"id": "d399fe5f-4fc8-4420-afc7-735f155b5a8e", "username": "Tanmay", "current_room": "3UM29", "score": 0, "is_admin": false, "joined_at": 1745529545.0476515}, "910a0741-a6a8-4eff-87ef-d31153b4596d": {"id": "910a0741-a6a8-4eff-87ef-d31153b4596d", "username": "Admin-82X", "current_room": "82X3G", "score": 0, "is_admin": true, "joined_at": 1745530156.7266526}, "fed0eae9-a455-491f-ab64-26d355c9cddb": {"id": "fed0eae9-a455-491f-ab64-26d355c9cddb", "username": "Tanmay", "current_room": "82X3G", "score": 0, "is_admin": false, "joined_at": 1745530188.8692076}, "ef88fa7d-7c09-40dc-8b4e-454cb284bf57": {"id": "ef88fa7d-7c09-40dc-8b4e-454cb284bf57", "username": "Admin-6SP", "current_room": "6SPG4", "score": 0, "is_admin": true, "joined_at": 1745530228.5777044}, "af3b3bf5-fbf8-4222-9fba-20ad858256bc": {"id": "af3b3bf5-fbf8-4222-9fba-20ad858256bc", "username": "Tanmay", "current_room": "6SPG4", "score": 0, "is_admin": false, "joined_at": 1745530241.953359}, "da51197a-43a8-4cd3-bc2e-b5e78662e962": {"id": "da51197a-43a8-4cd3-bc2e-b5e78662e962", "username": "Admin-KDE", "current_room": "KDEAM", "score": 0, "is_admin": true, "joined_at": 1745530480.4714289}, "2882656b-7f4c-4991-a2ca-8f50b251c69a": {"id": "2882656b-7f4c-4991-a2ca-8f50b251c69a", "username": "Admin-PXD", "current_room": "PXDSF", "score": 0, "is_admin": true, "joined_at": 1745530687.1789806}, "5938291e-b307-45bf-a204-f1e08f75b9d8": {"id": "5938291e-b307-45bf-a204-f1e08f75b9d8", "username": "Admin-3EH", "current_room": "3EHYK", "score": 0, "is_admin": true, "joined_at": 1745530773.2835586}, "65bf1e86-a2bc-4a8c-925c-9128f785509a": {"id": "65bf1e86-a2bc-4a8c-925c-9128f785509a", "username": "Tanmay", "current_room": "3EHYK", "score": 0, "is_admin": false, "joined_at": 1745530787.712024}, "159cb1fa-2521-4363-b67c-d94ebca57859": {"id": "159cb1fa-2521-4363-b67c-d94ebca57859", "username": "Admin-NMJ", "current_room": "NMJJU", "score": 0, "is_admin": true, "joined_at": 1745531672.6848013}, "06cf0080-946e-4fa8-8c84-021cb5d8aa58": {"id": "06cf0080-946e-4fa8-8c84-021cb5d8aa58", "username": "Admin-7N6", "current_room": "7N6DC", "score": 0, "is_admin": true, "joined_at": 1745531748.3711407}, "de7e57fa-0972-40f2-aec3-304cfab4673d": {"id": "de7e57fa-0972-40f2-aec3-304cfab4673d", "username": "Admin-FB7", "current_room": "FB72W", "score": 0, "is_admin": true, "joined_at": 1745532348.3142745}}}